napari_split_dataset/__init__.py
napari_split_dataset/napari.yaml
napari_split_dataset/napari_split_dataset.py
tests/__init__.py
tests/test_napari_split_dataset.py
tests/assets/array.h5
tests/assets/dict_shift.h5
tests/assets/dict_stack.h5
tests/assets/nodict.h5
tests/assets/random/empty.txt
tests/assets/sample_3d/0000.h5
tests/assets/sample_3d/0001.h5
tests/assets/sample_3d/0002.h5
tests/assets/sample_3d/0003.h5
tests/assets/sample_3d/stack_metadata.json
tests/assets/sample_4d/0000.h5
tests/assets/sample_4d/0001.h5
tests/assets/sample_4d/0002.h5
tests/assets/sample_4d/stack_metadata.json
napari_split_dataset-0.3.0.dist-info/METADATA
napari_split_dataset-0.3.0.dist-info/WHEEL
napari_split_dataset-0.3.0.dist-info/entry_points.txt
napari_split_dataset-0.3.0.dist-info/top_level.txt
napari_split_dataset-0.3.0.dist-info/RECORD
