Metadata-Version: 2.1
Name: napari-split-dataset
Version: 0.3.0
Summary: split-dataset/hdf5 file reader for napari
Home-page: https://github.com/portugueslab/napari-split-dataset
Author: You Wu @portugueslab
Author-email: youkwu@neuro.mpg.de
License: MIT
Classifier: Development Status :: 2 - Pre-Alpha
Classifier: Intended Audience :: Developers
Classifier: License :: OSI Approved :: MIT License
Classifier: Natural Language :: English
Classifier: Programming Language :: Python :: 3
Classifier: Programming Language :: Python :: 3.7
Classifier: Programming Language :: Python :: 3.8
Classifier: Programming Language :: Python :: 3.9
Classifier: Programming Language :: Python :: 3.10
Requires-Python: >=3.7
Requires-Dist: numpy
Requires-Dist: flammkuchen
Requires-Dist: split-dataset
Provides-Extra: dev
Requires-Dist: pytest ; extra == 'dev'
Requires-Dist: pytest-cov ; extra == 'dev'
Requires-Dist: black ; extra == 'dev'
Requires-Dist: flake8 ; extra == 'dev'
Requires-Dist: isort ; extra == 'dev'
